python_mpv_jsonipc.py
python_mpv_jsonipc-1.2.0.dist-info/LICENSE.md
python_mpv_jsonipc-1.2.0.dist-info/METADATA
python_mpv_jsonipc-1.2.0.dist-info/WHEEL
python_mpv_jsonipc-1.2.0.dist-info/top_level.txt
python_mpv_jsonipc-1.2.0.dist-info/RECORD
