Metadata-Version: 2.1
Name: python-mpv-jsonipc
Version: 1.2.0
Summary: Python API to MPV using JSON IPC
Home-page: https://github.com/iwalton3/python-mpv-jsonipc
Author: Ian Walton
Author-email: iwalton3@gmail.com
License: Apache-2.0
Platform: UNKNOWN
Classifier: Programming Language :: Python :: 3
Classifier: License :: OSI Approved :: Apache Software License
Classifier: Operating System :: OS Independent
Requires-Python: >=3.6
